{
  "number": "413",
  "title_cn": "等差数列划分",
  "title_en": "Arithmetic Slices",
  "slug": "arithmetic-slices",
  "difficulty": "Medium",
  "description": "如果一个数列 至少有三个元素 ，并且任意两个相邻元素之差相同，则称该数列为等差数列。\n\n\t例如，[1,3,5,7,9]、[7,7,7,7] 和 [3,-1,-5,-9] 都是等差数列。\n\n给你一个整数数组 nums ，返回数组 nums 中所有为等差数组的 子数组 个数。\n\n子数组 是数组中的一个连续序列。\n\n示例 1：\n\n输入：nums = [1,2,3,4]\n输出：3\n解释：nums 中有三个子等差数组：[1, 2, 3]、[2, 3, 4] 和 [1,2,3,4] 自身。\n\n示例 2：\n\n输入：nums = [1]\n输出：0\n\n提示：\n\n\t1 \n\t-1000",
  "constraints": [
    "1",
    "-1000"
  ]
}